sabotage/__init__.py
sabotage/_docker_utils.py
sabotage/_sabotaged_container.py
sabotage/_sabotaged_network.py
sabotage/py.typed
sabotage-1.0.1.dist-info/LICENSE.txt
sabotage-1.0.1.dist-info/METADATA
sabotage-1.0.1.dist-info/WHEEL
sabotage-1.0.1.dist-info/top_level.txt
sabotage-1.0.1.dist-info/RECORD
