Metadata-Version: 2.1
Name: sabotage
Version: 1.0.1
Summary: Simulates Docker container and network failures to test application resilience and fault tolerance
Home-page: https://github.com/tsv1/sabotage
Author: Nikita Tsvetkov
Author-email: tsv1@fastmail.com
License: Apache-2.0
Classifier: License :: OSI Approved :: Apache Software License
Classifier: Programming Language :: Python :: 3.8
Classifier: Programming Language :: Python :: 3.9
Classifier: Programming Language :: Python :: 3.10
Classifier: Programming Language :: Python :: 3.11
Classifier: Programming Language :: Python :: 3.12
Classifier: Typing :: Typed
Requires-Python: >=3.8
License-File: LICENSE.txt
Requires-Dist: aiodocker <1.0,>=0.21
